secret_loader/__init__.py
secret_loader/__main__.py
secret_loader/base.py
secret_loader/cli.py
secret_loader/exceptions.py
secret_loader/loaders.py
secret_loader/secrets.py
secret_loader-0.6.dist-info/entry_points.txt
secret_loader-0.6.dist-info/COPYING
secret_loader-0.6.dist-info/WHEEL
secret_loader-0.6.dist-info/METADATA
secret_loader-0.6.dist-info/RECORD
