Metadata-Version: 2.1
Name: secret_loader
Version: 0.6
Summary: Flexible Secret Loader to load secrets from any source with a simple API!
Home-page: https://github.com/JimFawkes/secret-loader
Author: Moritz Eilfort
Author-email: secret-loader@jimfawkes.com
Requires-Python: >=3.9
Classifier: Intended Audience :: Developers
Classifier: Natural Language :: English
Classifier: License :: OSI Approved :: GNU General Public License v3 or later (GPLv3+)
Classifier: Programming Language :: Python :: 3.9
Classifier: Programming Language :: Python :: 3.10
Classifier: Programming Language :: Python :: 3.11
Classifier: Topic :: Software Development :: Libraries :: Python Modules
Requires-Dist: boto3 <1.27, >1.13
Requires-Dist: python-dotenv <0.22, >0.13
Requires-Dist: pytest==7.2.0 ; extra == "test"
Requires-Dist: pytest-cov==4.0.0 ; extra == "test"
Provides-Extra: test
